sciopy/EIT_16_32_64_128.py
sciopy/ISX_3.py
sciopy/__init__.py
sciopy/com_util.py
sciopy/doteit.py
sciopy/meshing.py
sciopy/sciopy_dataclasses.py
sciopy/visualization.py
sciopy-0.8.2.dist-info/LICENSE
sciopy-0.8.2.dist-info/METADATA
sciopy-0.8.2.dist-info/WHEEL
sciopy-0.8.2.dist-info/top_level.txt
sciopy-0.8.2.dist-info/RECORD
