Metadata-Version: 2.1
Name: sciopy
Version: 0.8.2
Summary: Python based interface module for communication with the Sciospec Electrical Impedance Tomography (EIT) device.
Home-page: https://github.com/spatialaudio/sciopy.git
Author: Jacob Peter Thönes
Author-email: jacob.thoenes@uni-rostock.de
Keywords: Sciospec,EIT,EIS
Platform: any
Classifier: Programming Language :: Python :: 3
Classifier: License :: OSI Approved :: MIT License
Classifier: Operating System :: OS Independent
License-File: LICENSE
